duepico/__init__.py
duepico/duepico.py
duelink_duepico_mp-0.0.8.dist-info/METADATA
duelink_duepico_mp-0.0.8.dist-info/WHEEL
duelink_duepico_mp-0.0.8.dist-info/top_level.txt
duelink_duepico_mp-0.0.8.dist-info/RECORD
