Metadata-Version: 2.1
Name: duelink-duepico-mp
Version: 0.0.8
Summary: GHI Electronics DUELink DuePico MicroPython Library.
Home-page: https://www.duelink.com/
Author: GHI Electronics
Author-email: support@ghielectronics.com
License: MIT
Classifier: Programming Language :: Python :: Implementation :: MicroPython
Requires-Dist: duelink-stdlib-mp
